AbuLangModule/__init__.py
AbuLangModule/abu_chess.py
AbuLangModule/abu_files.py
AbuLangModule/abu_install.py
AbuLangModule/abu_smart.py
abulang-3.2.4.dist-info/METADATA
abulang-3.2.4.dist-info/WHEEL
abulang-3.2.4.dist-info/top_level.txt
abulang-3.2.4.dist-info/RECORD
