Metadata-Version: 2.4
Name: AbuLang
Version: 3.2.4
Summary: Complete AbuLang integration for Python IDLE - All commands work natively
Author: Abu
Author-email: abu.shariffaiml@gmail.com
Classifier: Programming Language :: Python :: 3
Classifier: Programming Language :: Python :: 3.8
Classifier: Programming Language :: Python :: 3.9
Classifier: Programming Language :: Python :: 3.10
Classifier: Programming Language :: Python :: 3.11
Classifier: Programming Language :: Python :: 3.12
Classifier: Programming Language :: Python :: 3.13
Classifier: License :: OSI Approved :: MIT License
Classifier: Operating System :: OS Independent
Classifier: Development Status :: 4 - Beta
Classifier: Intended Audience :: Education
Classifier: Intended Audience :: Developers
Requires-Python: >=3.8
Requires-Dist: PyYAML>=5.4
Provides-Extra: full
Requires-Dist: psutil>=5.8.0; extra == "full"
Requires-Dist: pyperclip>=1.8.2; extra == "full"
Requires-Dist: opencv-python>=4.5.0; extra == "full"
Provides-Extra: chess
Requires-Dist: python-chess>=1.9.0; extra == "chess"
Requires-Dist: torch>=1.9.0; extra == "chess"
Requires-Dist: flask>=2.0.0; extra == "chess"
Requires-Dist: flask-cors>=3.0.0; extra == "chess"
Dynamic: author
Dynamic: author-email
Dynamic: classifier
Dynamic: description
Dynamic: description-content-type
Dynamic: provides-extra
Dynamic: requires-dist
Dynamic: requires-python
Dynamic: summary
